cdk_static_wordpress/__init__.py
cdk_static_wordpress/py.typed
cdk_static_wordpress/_jsii/__init__.py
cdk_static_wordpress/_jsii/cdk-static-wordpress@0.1.18.jsii.tgz
cdk_static_wordpress-0.1.18.dist-info/LICENSE
cdk_static_wordpress-0.1.18.dist-info/METADATA
cdk_static_wordpress-0.1.18.dist-info/WHEEL
cdk_static_wordpress-0.1.18.dist-info/top_level.txt
cdk_static_wordpress-0.1.18.dist-info/RECORD
