Metadata-Version: 2.1
Name: cdk-static-wordpress
Version: 0.1.18
Summary: Generate a static site from Wordpress (via WP2Static) using AWS CDK
Home-page: https://github.com/blimmer/cdk-static-wordpress.git
Author: Ben Limmer<hello@benlimmer.com>
License: Apache-2.0
Project-URL: Source, https://github.com/blimmer/cdk-static-wordpress.git
Classifier: Intended Audience :: Developers
Classifier: Operating System :: OS Independent
Classifier: Programming Language :: JavaScript
Classifier: Programming Language :: Python :: 3 :: Only
Classifier: Programming Language :: Python :: 3.8
Classifier: Programming Language :: Python :: 3.9
Classifier: Programming Language :: Python :: 3.10
Classifier: Programming Language :: Python :: 3.11
Classifier: Typing :: Typed
Classifier: Development Status :: 7 - Inactive
Classifier: License :: OSI Approved
Requires-Python: ~=3.8
License-File: LICENSE
Requires-Dist: aws-cdk-lib <3.0.0,>=2.59.0
Requires-Dist: constructs <11.0.0,>=10.0.5
Requires-Dist: jsii <2.0.0,>=1.98.0
Requires-Dist: publication >=0.0.3
Requires-Dist: typeguard ~=2.13.3
